plants_vs_zombies/__init__.py
plants_vs_zombies/__main__.py
plants_vs_zombies/constants.py
plants_vs_zombies/tool.py
plants_vs_zombies/component/__init__.py
plants_vs_zombies/component/map.py
plants_vs_zombies/component/menubar.py
plants_vs_zombies/component/plant.py
plants_vs_zombies/component/zombie.py
plants_vs_zombies/data/entity/plant.json
plants_vs_zombies/data/entity/zombie.json
plants_vs_zombies/data/map/level_0.json
plants_vs_zombies/data/map/level_1.json
plants_vs_zombies/data/map/level_2.json
plants_vs_zombies/data/map/level_3.json
plants_vs_zombies/data/map/level_4.json
plants_vs_zombies/data/map/level_5.json
plants_vs_zombies/resources/graphics/Bullets/BulletMushRoom/BulletMushRoom_0.png
plants_vs_zombies/resources/graphics/Bullets/BulletMushRoom/BulletMushRoom_1.png
plants_vs_zombies/resources/graphics/Bullets/BulletMushRoom/BulletMushRoom_2.png
plants_vs_zombies/resources/graphics/Bullets/BulletMushRoom/BulletMushRoom_3.png
plants_vs_zombies/resources/graphics/Bullets/BulletMushRoom/BulletMushRoom_4.png
plants_vs_zombies/resources/graphics/Bullets/BulletMushRoomExplode/BulletMushRoomExplode_0.gif
plants_vs_zombies/resources/graphics/Bullets/PeaIce/PeaIce_0.png
plants_vs_zombies/resources/graphics/Bullets/PeaNormal/PeaNormal_0.png
plants_vs_zombies/resources/graphics/Bullets/PeaNormalExplode/PeaNormalExplode_0.png
plants_vs_zombies/resources/graphics/Cards/card_cherrybomb.png
plants_vs_zombies/resources/graphics/Cards/card_cherrybomb_move.png
plants_vs_zombies/resources/graphics/Cards/card_chomper.png
plants_vs_zombies/resources/graphics/Cards/card_chomper_move.png
plants_vs_zombies/resources/graphics/Cards/card_hypnoshroom.png
plants_vs_zombies/resources/graphics/Cards/card_iceshroom.png
plants_vs_zombies/resources/graphics/Cards/card_jalapeno.png
plants_vs_zombies/resources/graphics/Cards/card_peashooter.png
plants_vs_zombies/resources/graphics/Cards/card_peashooter_move.png
plants_vs_zombies/resources/graphics/Cards/card_potatomine.png
plants_vs_zombies-0.0.5.dist-info/METADATA
plants_vs_zombies-0.0.5.dist-info/WHEEL
plants_vs_zombies-0.0.5.dist-info/entry_points.txt
plants_vs_zombies-0.0.5.dist-info/top_level.txt
plants_vs_zombies-0.0.5.dist-info/RECORD
